check_os_ver-0.4.3.dist-info/METADATA
check_os_ver-0.4.3.dist-info/WHEEL
check_os_ver-0.4.3.dist-info/entry_points.txt
check_os_ver/__init__.py
check_os_ver/hi.py
check_os_ver/osver.py
check_os_ver-0.4.3.dist-info/RECORD
