Metadata-Version: 2.1
Name: check_os_ver
Version: 0.4.3
Summary: Default template for PDM package
Author-Email: vhzkclq0705 <vhzkclq0705@naver.com>, vhzkclq0705 <dhwns1513@gmail.com>
License: MIT
Project-URL: Homepage, https://github.com/vhzkclq0705/check_os_ver
Project-URL: Issues, https://github.com/vhzkclq0705/check_os_ver/issues
Requires-Python: >=3.10
Requires-Dist: check_os_ver
Requires-Dist: cho-check-os-ver
Requires-Dist: hj-check-os-version
Requires-Dist: jacob-os-version-check
Requires-Dist: lucas-check-os-ver
Requires-Dist: nunininu-check-os-ver
Requires-Dist: ppabam-check-os-ver>=0.2.0
Requires-Dist: seo-check-os-version
Requires-Dist: stundrg-check-os-ver
